{"word": "POS", "polygon": [[1073, 320], [1053, 312], [1067, 267], [1088, 274]]}
{"word": "Date", "polygon": [[1044, 322], [1025, 315], [1043, 259], [1062, 265]]}
{"word": "Table", "polygon": [[992, 399], [956, 384], [998, 244], [1036, 257]]}
{"word": "Invoice", "polygon": [[1080, 384], [1059, 376], [1090, 278], [1112, 286]]}
{"word": "Pu", "polygon": [[678, 195], [660, 189], [667, 159], [686, 166]]}
{"word": "Red", "polygon": [[907, 287], [890, 281], [902, 238], [919, 244]]}
{"word": "Rice", "polygon": [[604, 195], [586, 189], [598, 137], [616, 143]]}
{"word": "Rice", "polygon": [[560, 181], [542, 175], [553, 123], [572, 129]]}
{"word": "Ginger", "polygon": [[832, 301], [809, 293], [830, 214], [853, 222]]}
{"word": "Beancurd", "polygon": [[775, 312], [756, 305], [784, 199], [804, 206]]}
{"word": "ITEM", "polygon": [[948, 310], [931, 304], [945, 256], [962, 262]]}
{"word": "G.", "polygon": [[750, 209], [732, 203], [736, 185], [755, 191]]}
{"word": "TOTAL", "polygon": [[381, 210], [348, 199], [370, 84], [403, 95]]}
{"word": "No:2", "polygon": [[1051, 389], [1031, 380], [1049, 324], [1070, 331]]}
{"word": "Rounding", "polygon": [[414, 214], [394, 207], [414, 104], [435, 111]]}
{"word": "Dragon", "polygon": [[728, 295], [707, 288], [727, 209], [748, 216]]}
{"word": "Sub", "polygon": [[491, 171], [473, 166], [481, 127], [499, 133]]}
{"word": "Service", "polygon": [[459, 214], [442, 208], [460, 120], [477, 126]]}
{"word": "Total", "polygon": [[444, 180], [426, 174], [438, 114], [456, 120]]}
{"word": "HOT", "polygon": [[620, 229], [603, 223], [612, 184], [630, 190]]}
{"word": "Er", "polygon": [[669, 232], [651, 225], [657, 200], [676, 206]]}
{"word": ":", "polygon": [[1030, 347], [1019, 342], [1021, 334], [1033, 339]]}
{"word": "(1-3)", "polygon": [[639, 258], [619, 251], [632, 196], [652, 202]]}
{"word": "Cat", "polygon": [[892, 339], [875, 332], [886, 292], [903, 299]]}
{"word": "Small", "polygon": [[542, 257], [525, 251], [539, 187], [557, 193]]}
{"word": "23/2/2018", "polygon": [[992, 488], [974, 480], [1012, 358], [1031, 365]]}
{"word": "(B)", "polygon": [[594, 243], [575, 237], [582, 206], [601, 213]]}
{"word": "MEDAN", "polygon": [[1191, 530], [1172, 521], [1198, 446], [1218, 454]]}
{"word": "Total", "polygon": [[475, 243], [458, 237], [470, 177], [488, 183]]}
{"word": ":", "polygon": [[1070, 408], [1051, 401], [1053, 393], [1072, 401]]}
{"word": "8884", "polygon": [[1052, 467], [1033, 459], [1051, 404], [1070, 412]]}
{"word": "(1-3)", "polygon": [[653, 304], [632, 296], [645, 241], [666, 249]]}
{"word": "Clams", "polygon": [[809, 381], [790, 374], [808, 307], [827, 314]]}
{"word": "Sales", "polygon": [[428, 256], [411, 249], [423, 187], [441, 193]]}
{"word": "ST", "polygon": [[676, 303], [658, 297], [665, 271], [682, 277]]}
{"word": "13,", "polygon": [[1222, 536], [1197, 525], [1210, 487], [1236, 497]]}
{"word": "Steamed", "polygon": [[822, 425], [804, 418], [829, 329], [847, 335]]}
{"word": "RESTAURANT", "polygon": [[1269, 733], [1243, 719], [1309, 541], [1337, 553]]}
{"word": "W", "polygon": [[769, 337], [749, 331], [753, 315], [773, 322]]}
{"word": "Chives", "polygon": [[705, 381], [687, 375], [707, 300], [725, 306]]}
{"word": "Fish", "polygon": [[872, 405], [856, 398], [872, 344], [888, 351]]}
{"word": "Chare", "polygon": [[443, 285], [425, 278], [437, 218], [456, 224]]}
{"word": "QTY", "polygon": [[910, 433], [895, 426], [906, 389], [921, 396]]}
{"word": "IR", "polygon": [[669, 329], [652, 322], [657, 300], [675, 306]]}
{"word": "Dao", "polygon": [[755, 386], [737, 380], [747, 341], [766, 347]]}
{"word": "JIAWEI", "polygon": [[1249, 680], [1220, 666], [1257, 563], [1288, 577]]}
{"word": "Bc", "polygon": [[467, 280], [450, 274], [455, 250], [472, 256]]}
{"word": "NIAGA", "polygon": [[1161, 616], [1141, 606], [1167, 533], [1187, 542]]}
{"word": "JLN", "polygon": [[1199, 599], [1177, 589], [1193, 546], [1214, 555]]}
{"word": "002693074-K", "polygon": [[1176, 769], [1149, 755], [1217, 564], [1246, 577]]}
{"word": "FRIED", "polygon": [[651, 403], [633, 396], [649, 332], [667, 338]]}
{"word": "1", "polygon": [[618, 334], [603, 328], [606, 318], [621, 324]]}
{"word": "Adjustment", "polygon": [[388, 339], [369, 332], [392, 216], [411, 222]]}
{"word": "(S)", "polygon": [[798, 424], [777, 417], [785, 386], [807, 394]]}
{"word": "57000", "polygon": [[1127, 631], [1106, 620], [1130, 550], [1152, 560]]}
{"word": "1", "polygon": [[841, 431], [827, 424], [830, 415], [844, 421]]}
{"word": "20:04:08", "polygon": [[955, 605], [938, 597], [970, 491], [988, 500]]}
{"word": "Gan(S)", "polygon": [[738, 470], [714, 461], [732, 389], [757, 398]]}
{"word": "INVOICE", "polygon": [[1067, 669], [1043, 656], [1079, 547], [1104, 558]]}
{"word": "(S)", "polygon": [[699, 415], [676, 406], [683, 377], [707, 386]]}
{"word": "U/P(RM)", "polygon": [[878, 548], [860, 539], [883, 460], [902, 468]]}
{"word": "13", "polygon": [[944, 554], [910, 538], [926, 484], [960, 500]]}
{"word": "LAS", "polygon": [[1168, 683], [1148, 673], [1172, 605], [1192, 615]]}
{"word": "1", "polygon": [[673, 408], [657, 402], [659, 392], [676, 398]]}
{"word": "DAMAI", "polygon": [[1134, 694], [1114, 684], [1138, 617], [1158, 626]]}
{"word": "Cashier:admin", "polygon": [[967, 731], [948, 721], [1002, 551], [1022, 561]]}
{"word": "1", "polygon": [[762, 454], [745, 447], [748, 437], [765, 444]]}
{"word": "1", "polygon": [[715, 436], [698, 430], [701, 420], [718, 426]]}
{"word": "}", "polygon": [[492, 366], [478, 360], [480, 349], [495, 355]]}
{"word": "42.", "polygon": [[819, 511], [804, 504], [812, 474], [828, 482]]}
{"word": "5.", "polygon": [[599, 416], [582, 410], [586, 390], [603, 396]]}
{"word": "HOUSE", "polygon": [[1211, 783], [1182, 768], [1213, 683], [1243, 698]]}
{"word": "KL", "polygon": [[1112, 670], [1093, 660], [1103, 631], [1122, 641]]}
{"word": "00", "polygon": [[486, 404], [469, 398], [474, 371], [492, 378]]}
{"word": "00", "polygon": [[592, 445], [575, 438], [581, 413], [598, 419]]}
{"word": "scount", "polygon": [[432, 431], [417, 426], [431, 358], [447, 364]]}
{"word": "UTAMA", "polygon": [[1139, 765], [1119, 754], [1144, 684], [1164, 695]]}
{"word": "00", "polygon": [[810, 545], [795, 537], [802, 510], [817, 518]]}
{"word": "RM", "polygon": [[343, 383], [315, 372], [323, 328], [351, 339]]}
{"word": "16.", "polygon": [[653, 486], [636, 480], [643, 451], [661, 457]]}
{"word": "JIAWEI", "polygon": [[1224, 851], [1198, 837], [1236, 735], [1262, 749]]}
{"word": "20.", "polygon": [[741, 536], [722, 529], [731, 496], [750, 503]]}
{"word": "50", "polygon": [[522, 443], [506, 437], [512, 412], [528, 419]]}
{"word": "18.", "polygon": [[695, 515], [677, 508], [684, 481], [702, 487]]}
{"word": "DISC(%)", "polygon": [[846, 649], [831, 640], [853, 564], [869, 572]]}
{"word": "SG", "polygon": [[1118, 737], [1098, 726], [1108, 698], [1128, 708]]}
{"word": "00", "polygon": [[646, 518], [628, 512], [635, 485], [652, 492]]}
{"word": "00", "polygon": [[733, 565], [715, 558], [722, 531], [740, 538]]}
{"word": "00", "polygon": [[687, 546], [669, 539], [676, 513], [694, 520]]}
{"word": "BESI", "polygon": [[1095, 800], [1076, 790], [1094, 738], [1113, 748]]}
{"word": "110.", "polygon": [[324, 479], [295, 468], [310, 390], [339, 401]]}
{"word": "0.", "polygon": [[470, 477], [453, 470], [457, 452], [473, 459]]}
{"word": "0.", "polygon": [[573, 519], [557, 513], [562, 494], [578, 500]]}
{"word": "8", "polygon": [[1129, 790], [1110, 779], [1115, 766], [1134, 776]]}
{"word": "RM", "polygon": [[424, 478], [408, 472], [413, 448], [429, 454]]}
{"word": "RM", "polygon": [[384, 462], [369, 456], [374, 432], [389, 438]]}
{"word": "0.", "polygon": [[788, 620], [773, 612], [778, 593], [793, 601]]}
{"word": "0.", "polygon": [[506, 516], [490, 510], [493, 492], [510, 498]]}
{"word": "00", "polygon": [[462, 507], [446, 501], [452, 476], [468, 482]]}
{"word": "00", "polygon": [[567, 549], [550, 542], [556, 517], [573, 524]]}
{"word": "00", "polygon": [[779, 651], [765, 642], [772, 616], [787, 625]]}
{"word": "RM", "polygon": [[399, 493], [384, 487], [389, 463], [404, 469]]}
{"word": "RM", "polygon": [[359, 477], [344, 471], [349, 447], [364, 453]]}
{"word": "0.", "polygon": [[628, 589], [611, 582], [615, 565], [632, 572]]}
{"word": "00", "polygon": [[499, 546], [483, 539], [488, 514], [505, 521]]}
{"word": "110.", "polygon": [[414, 527], [398, 520], [406, 483], [422, 489]]}
{"word": "110.", "polygon": [[374, 512], [358, 506], [366, 467], [382, 474]]}
{"word": "Amt(RM)", "polygon": [[818, 748], [801, 737], [822, 665], [840, 675]]}
{"word": "0.", "polygon": [[668, 619], [650, 611], [655, 594], [673, 601]]}
{"word": "0.", "polygon": [[712, 638], [695, 631], [700, 613], [717, 620]]}
{"word": "0.", "polygon": [[393, 520], [378, 513], [382, 495], [397, 501]]}
{"word": "0.", "polygon": [[355, 502], [339, 495], [342, 480], [358, 487]]}
{"word": "00", "polygon": [[619, 620], [603, 613], [609, 589], [626, 596]]}
{"word": "00", "polygon": [[704, 668], [687, 660], [693, 635], [711, 642]]}
{"word": "00", "polygon": [[660, 649], [642, 642], [649, 617], [667, 624]]}
{"word": "00", "polygon": [[315, 527], [287, 516], [295, 473], [323, 484]]}
{"word": "00", "polygon": [[407, 556], [391, 549], [396, 525], [412, 532]]}
{"word": "3", "polygon": [[450, 562], [434, 556], [437, 542], [453, 549]]}
{"word": "00", "polygon": [[388, 548], [372, 541], [377, 518], [392, 524]]}
{"word": "00", "polygon": [[368, 540], [352, 533], [357, 510], [373, 516]]}
{"word": "00", "polygon": [[348, 532], [333, 526], [337, 502], [353, 508]]}
{"word": "42.", "polygon": [[762, 712], [748, 703], [756, 674], [770, 683]]}
{"word": "5.", "polygon": [[552, 608], [535, 601], [539, 585], [556, 592]]}
{"word": "0", "polygon": [[547, 627], [531, 620], [534, 606], [551, 613]]}
{"word": "0", "polygon": [[445, 585], [429, 578], [432, 564], [448, 571]]}
{"word": "6", "polygon": [[485, 601], [470, 594], [473, 582], [488, 588]]}
{"word": ":", "polygon": [[963, 467], [934, 454], [938, 440], [968, 453]]}
{"word": "", "polygon": [[1061, 529], [1042, 521], [1103, 334], [1122, 341]]}
{"word": "", "polygon": [[961, 834], [944, 824], [1027, 567], [1046, 576]]}
{"word": "", "polygon": [[837, 757], [822, 748], [962, 276], [980, 283]]}
{"word": "", "polygon": [[800, 737], [784, 727], [914, 274], [933, 281]]}
{"word": "", "polygon": [[289, 508], [271, 500], [351, 69], [371, 76]]}
{"word": "-", "polygon": [[1129, 306], [1118, 302], [1123, 285], [1135, 289]]}
{"word": "-", "polygon": [[1123, 325], [1113, 322], [1119, 303], [1129, 306]]}
{"word": "-", "polygon": [[1119, 338], [1108, 334], [1113, 319], [1123, 323]]}
{"word": "-", "polygon": [[976, 281], [967, 278], [970, 265], [980, 269]]}
{"word": "-", "polygon": [[980, 267], [971, 264], [975, 251], [984, 254]]}
{"word": "-", "polygon": [[984, 254], [974, 251], [979, 235], [989, 239]]}
{"word": "-", "polygon": [[930, 279], [922, 276], [925, 263], [934, 266]]}
{"word": "-", "polygon": [[934, 265], [926, 262], [929, 250], [937, 253]]}
{"word": "-", "polygon": [[939, 254], [929, 250], [933, 236], [943, 240]]}
{"word": "-", "polygon": [[943, 240], [933, 236], [937, 224], [947, 227]]}
{"word": "*", "polygon": [[368, 77], [353, 73], [356, 60], [370, 65]]}
{"word": "*", "polygon": [[371, 63], [357, 59], [359, 47], [373, 51]]}
{"word": "*", "polygon": [[372, 52], [358, 47], [361, 34], [375, 38]]}
