{"word": "of", "polygon": [[1396, 1074], [1370, 1073], [1378, 1045], [1405, 1047]]}
{"word": "the", "polygon": [[1359, 1072], [1309, 1070], [1317, 1044], [1366, 1046]]}
{"word": "elderly", "polygon": [[1296, 1070], [1190, 1061], [1205, 1030], [1308, 1037]]}
{"word": "Angles", "polygon": [[1409, 1038], [1324, 1033], [1334, 998], [1425, 1007]]}
{"word": "In", "polygon": [[1314, 1030], [1289, 1029], [1297, 1007], [1321, 1007]]}
{"word": "The", "polygon": [[1276, 1030], [1221, 1026], [1230, 1003], [1285, 1007]]}
{"word": "running", "polygon": [[1427, 1003], [1320, 993], [1322, 953], [1436, 968]]}
{"word": "running", "polygon": [[1309, 993], [1200, 985], [1209, 949], [1311, 952]]}
{"word": "The", "polygon": [[1437, 962], [1378, 952], [1379, 925], [1437, 934]]}
{"word": "Mclaren", "polygon": [[1364, 953], [1253, 946], [1256, 913], [1365, 921]]}
{"word": "sumepet@fadanif.edu", "polygon": [[1123, 1048], [938, 1033], [943, 1018], [1129, 1035]]}
{"word": "32", "polygon": [[925, 1034], [905, 1037], [909, 1025], [928, 1023]]}
{"word": "new", "polygon": [[1131, 1031], [1092, 1022], [1096, 1015], [1135, 1025]]}
{"word": "bei", "polygon": [[1075, 1021], [1048, 1017], [1053, 1008], [1080, 1012]]}
{"word": "ist", "polygon": [[1034, 1016], [1014, 1016], [1019, 1007], [1039, 1007]]}
{"word": "GB", "polygon": [[1001, 1016], [979, 1016], [983, 1006], [1006, 1006]]}
{"word": "vielen", "polygon": [[965, 1016], [917, 1019], [921, 1008], [969, 1006]]}
{"word": "3", "polygon": [[904, 1021], [894, 1022], [897, 1010], [907, 1009]]}
{"word": "z", "polygon": [[881, 1020], [873, 1020], [875, 1012], [884, 1011]]}
{"word": "07/03/18", "polygon": [[1137, 1021], [1048, 1004], [1055, 995], [1144, 1011]]}
{"word": "56", "polygon": [[1035, 1003], [1015, 1003], [1021, 995], [1041, 995]]}
{"word": "82", "polygon": [[1001, 1003], [980, 1002], [986, 993], [1007, 994]]}
{"word": "(388)", "polygon": [[966, 1003], [922, 1004], [927, 989], [973, 990]]}
{"word": "MERCADO.", "polygon": [[836, 1037], [565, 1013], [571, 979], [844, 1006]]}
{"word": "95", "polygon": [[846, 996], [782, 988], [789, 955], [854, 964]]}
{"word": "SSID", "polygon": [[769, 986], [648, 970], [656, 940], [776, 953]]}
{"word": "pp", "polygon": [[637, 962], [572, 961], [578, 925], [645, 932]]}
{"word": "Kabelnetz", "polygon": [[856, 956], [596, 924], [603, 891], [865, 924]]}
{"word": "87", "polygon": [[867, 912], [805, 904], [812, 870], [872, 876]]}
{"word": "716,930", "polygon": [[793, 902], [594, 877], [602, 837], [801, 862]]}
{"word": "I", "polygon": [[581, 875], [566, 873], [572, 841], [587, 843]]}
{"word": "S\u00c9JOURS", "polygon": [[872, 879], [628, 850], [638, 802], [879, 830]]}
{"word": "REVIEWER", "polygon": [[1441, 785], [1258, 760], [1267, 734], [1447, 760]]}
{"word": "THE", "polygon": [[1468, 715], [1404, 705], [1411, 678], [1479, 690]]}
{"word": "VINYL", "polygon": [[1369, 699], [1255, 681], [1257, 653], [1372, 672]]}
{"word": "M\u00c9DI\u00c9VAUX", "polygon": [[1484, 653], [1252, 612], [1252, 574], [1482, 615]]}
{"word": "diese", "polygon": [[1198, 755], [1127, 745], [1130, 726], [1202, 736]]}
{"word": "ins", "polygon": [[1118, 744], [1076, 738], [1081, 719], [1122, 725]]}
{"word": "Ihr", "polygon": [[1068, 737], [1025, 732], [1029, 712], [1073, 718]]}
{"word": "wir", "polygon": [[1017, 731], [970, 725], [974, 705], [1021, 711]]}
{"word": "1,", "polygon": [[962, 723], [935, 719], [938, 695], [966, 699]]}
{"word": "Haz", "polygon": [[1203, 730], [1153, 723], [1155, 704], [1206, 712]]}
{"word": "TAILANDIA", "polygon": [[1144, 721], [987, 699], [990, 680], [1147, 703]]}
{"word": "the", "polygon": [[1207, 707], [1163, 700], [1165, 681], [1210, 688]]}
{"word": "Y", "polygon": [[1155, 698], [1136, 695], [1139, 677], [1157, 680]]}
{"word": "O", "polygon": [[1129, 694], [1111, 691], [1114, 673], [1131, 676]]}
{"word": "repeated", "polygon": [[1102, 691], [982, 673], [985, 647], [1107, 666]]}
{"word": "prominent", "polygon": [[909, 717], [682, 683], [687, 653], [912, 688]]}
{"word": "asian", "polygon": [[912, 686], [789, 667], [792, 639], [914, 657]]}
{"word": "and", "polygon": [[767, 664], [681, 651], [687, 622], [771, 635]]}
{"word": "Knowledge", "polygon": [[914, 656], [668, 618], [673, 589], [917, 628]]}
{"word": "noting", "polygon": [[917, 627], [781, 605], [787, 577], [921, 599]]}
{"word": "the", "polygon": [[761, 602], [685, 590], [691, 560], [767, 573]]}
{"word": "And", "polygon": [[921, 598], [842, 585], [846, 557], [924, 570]]}
{"word": "Resulted", "polygon": [[822, 581], [616, 547], [621, 517], [827, 553]]}
{"word": "Deinem", "polygon": [[1492, 502], [1413, 485], [1414, 466], [1495, 483]]}
{"word": "v", "polygon": [[1384, 475], [1368, 472], [1371, 457], [1387, 460]]}
{"word": "8.", "polygon": [[1336, 469], [1304, 465], [1309, 447], [1341, 452]]}
{"word": "television", "polygon": [[1499, 457], [1365, 428], [1368, 409], [1502, 439]]}
{"word": "5,", "polygon": [[1336, 420], [1307, 414], [1313, 391], [1341, 398]]}
{"word": "1", "polygon": [[1503, 411], [1489, 408], [1491, 392], [1504, 395]]}
{"word": "c", "polygon": [[1461, 401], [1447, 398], [1450, 384], [1464, 387]]}
{"word": "d", "polygon": [[1420, 397], [1406, 393], [1408, 375], [1422, 378]]}
{"word": "O.", "polygon": [[1381, 384], [1355, 378], [1355, 362], [1381, 369]]}
{"word": "5", "polygon": [[1329, 371], [1316, 367], [1317, 351], [1330, 355]]}
{"word": "7", "polygon": [[1503, 369], [1490, 365], [1489, 350], [1502, 354]]}
{"word": "dd", "polygon": [[1466, 361], [1437, 354], [1440, 335], [1467, 343]]}
{"word": "barri\u00e8res", "polygon": [[1409, 349], [1291, 317], [1291, 299], [1413, 329]]}
{"word": "D'ENGAGER", "polygon": [[1226, 449], [1034, 398], [1036, 372], [1233, 424]]}
{"word": "boluwac.co.uk", "polygon": [[1235, 415], [1010, 358], [1010, 334], [1244, 388]]}
{"word": "1", "polygon": [[1247, 379], [1231, 374], [1236, 349], [1253, 353]]}
{"word": "5671", "polygon": [[1223, 372], [1145, 355], [1150, 329], [1228, 346]]}
{"word": "1,764", "polygon": [[1135, 353], [1047, 333], [1052, 302], [1142, 322]]}
{"word": "1", "polygon": [[1254, 345], [1238, 340], [1239, 316], [1256, 321]]}
{"word": "891", "polygon": [[1229, 338], [1175, 325], [1179, 299], [1231, 314]]}
{"word": "101", "polygon": [[1165, 323], [1108, 310], [1115, 282], [1170, 297]]}
{"word": "p", "polygon": [[1100, 301], [1078, 296], [1086, 267], [1108, 272]]}
{"word": "2", "polygon": [[1067, 301], [1047, 297], [1053, 270], [1074, 273]]}
{"word": "zowop.co.uk", "polygon": [[1256, 313], [1058, 260], [1062, 227], [1256, 283]]}
{"word": "since", "polygon": [[955, 375], [877, 358], [878, 337], [956, 354]]}
{"word": "the", "polygon": [[861, 361], [804, 347], [806, 321], [862, 335]]}
{"word": "early", "polygon": [[787, 344], [687, 327], [693, 288], [790, 307]]}
{"word": "rare", "polygon": [[957, 326], [887, 312], [888, 297], [957, 310]]}
{"word": "khurja", "polygon": [[872, 316], [766, 291], [770, 255], [875, 280]]}
{"word": "is", "polygon": [[750, 281], [721, 275], [723, 254], [752, 261]]}
{"word": "in", "polygon": [[961, 279], [931, 273], [933, 256], [963, 262]]}
{"word": "company", "polygon": [[916, 267], [780, 234], [784, 206], [919, 241]]}
{"word": "nd", "polygon": [[762, 240], [720, 230], [724, 204], [766, 215]]}
{"word": "Quilty", "polygon": [[964, 239], [860, 213], [863, 178], [966, 206]]}
{"word": "Leaves", "polygon": [[845, 207], [739, 177], [745, 148], [848, 182]]}
{"word": "On", "polygon": [[723, 173], [685, 164], [690, 138], [728, 147]]}
