{"word": "of", "polygon": [[1252, 18], [1251, 61], [1222, 68], [1221, 26]]}
{"word": "the", "polygon": [[1250, 80], [1248, 157], [1224, 162], [1224, 86]]}
{"word": "elderly", "polygon": [[1250, 176], [1250, 323], [1213, 325], [1217, 181]]}
{"word": "Angles", "polygon": [[1209, 28], [1213, 159], [1174, 165], [1165, 34]]}
{"word": "In", "polygon": [[1208, 178], [1206, 216], [1179, 218], [1183, 181]]}
{"word": "The", "polygon": [[1207, 234], [1206, 309], [1181, 310], [1179, 236]]}
{"word": "running", "polygon": [[1160, 35], [1166, 189], [1129, 193], [1125, 43]]}
{"word": "running", "polygon": [[1164, 206], [1163, 355], [1122, 356], [1128, 210]]}
{"word": "The", "polygon": [[1120, 44], [1128, 120], [1105, 124], [1100, 51]]}
{"word": "Mclaren", "polygon": [[1130, 137], [1122, 296], [1094, 298], [1103, 142]]}
{"word": "sumepet@fadanif.edu", "polygon": [[1274, 398], [1268, 627], [1254, 625], [1253, 398]]}
{"word": "32", "polygon": [[1267, 645], [1265, 672], [1255, 669], [1257, 642]]}
{"word": "new", "polygon": [[1247, 398], [1256, 438], [1244, 438], [1236, 398]]}
{"word": "bei", "polygon": [[1263, 455], [1263, 487], [1247, 487], [1247, 455]]}
{"word": "ist", "polygon": [[1261, 505], [1258, 531], [1244, 531], [1246, 504]]}
{"word": "GB", "polygon": [[1256, 549], [1254, 578], [1241, 577], [1242, 548]]}
{"word": "vielen", "polygon": [[1253, 596], [1252, 658], [1241, 655], [1241, 594]]}
{"word": "3", "polygon": [[1250, 675], [1248, 689], [1237, 687], [1239, 673]]}
{"word": "z", "polygon": [[1243, 706], [1241, 717], [1233, 715], [1235, 705]]}
{"word": "07/03/18", "polygon": [[1229, 399], [1240, 496], [1223, 496], [1211, 399]]}
{"word": "56", "polygon": [[1239, 513], [1237, 539], [1222, 539], [1224, 513]]}
{"word": "82", "polygon": [[1236, 557], [1236, 583], [1222, 582], [1222, 556]]}
{"word": "(388)", "polygon": [[1237, 600], [1237, 655], [1218, 653], [1218, 599]]}
{"word": "MERCADO.", "polygon": [[1252, 760], [1262, 1027], [1235, 1014], [1223, 753]]}
{"word": "95", "polygon": [[1214, 751], [1211, 818], [1182, 812], [1181, 747]]}
{"word": "SSID", "polygon": [[1212, 830], [1226, 939], [1193, 933], [1182, 824]]}
{"word": "pp", "polygon": [[1221, 949], [1222, 1010], [1195, 998], [1188, 943]]}
{"word": "Kabelnetz", "polygon": [[1171, 747], [1192, 982], [1158, 978], [1136, 744]]}
{"word": "87", "polygon": [[1126, 742], [1127, 803], [1099, 797], [1101, 736]]}
{"word": "716,930", "polygon": [[1127, 815], [1148, 985], [1108, 980], [1093, 808]]}
{"word": "I", "polygon": [[1149, 996], [1150, 1008], [1118, 1004], [1117, 992]]}
{"word": "S\u00c9JOURS", "polygon": [[1103, 736], [1115, 958], [1072, 951], [1069, 728]]}
{"word": "REVIEWER", "polygon": [[982, 80], [977, 325], [948, 326], [956, 83]]}
{"word": "THE", "polygon": [[899, 86], [896, 175], [869, 177], [868, 87]]}
{"word": "VINYL", "polygon": [[898, 217], [899, 358], [878, 359], [876, 220]]}
{"word": "M\u00c9DI\u00c9VAUX", "polygon": [[835, 92], [851, 367], [826, 368], [810, 98]]}
{"word": "diese", "polygon": [[973, 401], [976, 480], [960, 480], [957, 402]]}
{"word": "ins", "polygon": [[977, 489], [976, 534], [959, 534], [960, 489]]}
{"word": "Ihr", "polygon": [[976, 543], [971, 593], [955, 592], [958, 543]]}
{"word": "wir", "polygon": [[970, 603], [968, 653], [953, 652], [954, 601]]}
{"word": "1,", "polygon": [[966, 662], [963, 693], [947, 690], [949, 660]]}
{"word": "Haz", "polygon": [[951, 402], [954, 457], [940, 457], [936, 402]]}
{"word": "TAILANDIA", "polygon": [[954, 466], [948, 638], [935, 636], [940, 465]]}
{"word": "the", "polygon": [[932, 402], [936, 449], [921, 449], [916, 402]]}
{"word": "Y", "polygon": [[935, 458], [935, 478], [921, 478], [921, 457]]}
{"word": "O", "polygon": [[934, 487], [934, 507], [919, 507], [920, 487]]}
{"word": "repeated", "polygon": [[934, 516], [931, 645], [913, 642], [914, 516]]}
{"word": "prominent", "polygon": [[959, 721], [977, 914], [960, 907], [943, 717]]}
{"word": "asian", "polygon": [[942, 717], [952, 824], [935, 818], [927, 712]]}
{"word": "and", "polygon": [[956, 840], [959, 912], [937, 908], [937, 835]]}
{"word": "Knowledge", "polygon": [[926, 711], [933, 927], [909, 925], [910, 708]]}
{"word": "noting", "polygon": [[909, 707], [912, 829], [890, 827], [890, 705]]}
{"word": "the", "polygon": [[912, 847], [909, 914], [887, 911], [889, 845]]}
{"word": "And", "polygon": [[889, 704], [891, 776], [871, 773], [871, 701]]}
{"word": "Resulted", "polygon": [[890, 795], [891, 968], [874, 961], [870, 792]]}
{"word": "Deinem", "polygon": [[715, 111], [720, 208], [705, 210], [697, 113]]}
{"word": "v", "polygon": [[721, 240], [723, 257], [710, 258], [708, 241]]}
{"word": "8.", "polygon": [[732, 288], [739, 319], [721, 320], [715, 289]]}
{"word": "television", "polygon": [[674, 115], [686, 272], [669, 273], [658, 116]]}
{"word": "5,", "polygon": [[687, 303], [690, 333], [667, 334], [665, 304]]}
{"word": "1", "polygon": [[634, 119], [635, 135], [619, 136], [618, 120]]}
{"word": "c", "polygon": [[637, 166], [640, 182], [625, 182], [623, 167]]}
{"word": "d", "polygon": [[647, 212], [648, 229], [631, 230], [630, 213]]}
{"word": "O.", "polygon": [[646, 259], [646, 290], [634, 290], [633, 260]]}
{"word": "5", "polygon": [[646, 320], [647, 335], [634, 335], [633, 320]]}
{"word": "7", "polygon": [[592, 122], [593, 139], [580, 140], [579, 123]]}
{"word": "dd", "polygon": [[597, 169], [602, 203], [585, 204], [581, 171]]}
{"word": "barri\u00e8res", "polygon": [[607, 234], [614, 368], [599, 369], [590, 234]]}
{"word": "D'ENGAGER", "polygon": [[741, 404], [726, 617], [707, 615], [718, 404]]}
{"word": "boluwac.co.uk", "polygon": [[709, 405], [704, 639], [689, 637], [682, 406]]}
{"word": "1", "polygon": [[674, 406], [672, 424], [650, 425], [651, 406]]}
{"word": "5671", "polygon": [[671, 434], [676, 510], [653, 511], [649, 434]]}
{"word": "1,764", "polygon": [[677, 519], [680, 603], [656, 602], [649, 520]]}
{"word": "1", "polygon": [[644, 406], [643, 425], [625, 425], [626, 407]]}
{"word": "891", "polygon": [[642, 434], [642, 490], [619, 490], [624, 434]]}
{"word": "101", "polygon": [[643, 499], [648, 552], [621, 554], [620, 499]]}
{"word": "p", "polygon": [[642, 562], [644, 582], [617, 583], [614, 563]]}
{"word": "2", "polygon": [[651, 590], [654, 608], [631, 608], [626, 591]]}
{"word": "zowop.co.uk", "polygon": [[619, 407], [622, 606], [595, 606], [595, 407]]}
{"word": "since", "polygon": [[727, 689], [731, 756], [720, 752], [714, 686]]}
{"word": "the", "polygon": [[734, 771], [734, 820], [719, 815], [720, 766]]}
{"word": "early", "polygon": [[735, 833], [750, 903], [725, 898], [716, 826]]}
{"word": "rare", "polygon": [[697, 683], [705, 740], [694, 738], [687, 681]]}
{"word": "khurja", "polygon": [[709, 754], [712, 842], [692, 835], [686, 750]]}
{"word": "is", "polygon": [[711, 853], [713, 875], [701, 871], [699, 848]]}
{"word": "in", "polygon": [[663, 680], [665, 705], [651, 704], [649, 679]]}
{"word": "company", "polygon": [[664, 718], [675, 828], [653, 827], [643, 716]]}
{"word": "nd", "polygon": [[683, 841], [686, 874], [666, 872], [664, 840]]}
{"word": "Quilty", "polygon": [[632, 678], [641, 765], [618, 761], [608, 675]]}
{"word": "Leaves", "polygon": [[641, 778], [643, 865], [622, 863], [624, 775]]}
{"word": "On", "polygon": [[643, 877], [647, 905], [626, 905], [624, 876]]}
