{"word": "of", "polygon": [[706, 1070], [693, 1046], [705, 1040], [718, 1066]]}
{"word": "the", "polygon": [[688, 1035], [666, 990], [676, 985], [699, 1030]]}
{"word": "elderly", "polygon": [[660, 979], [622, 892], [630, 887], [672, 973]]}
{"word": "Angles", "polygon": [[721, 1064], [682, 986], [697, 979], [733, 1061]]}
{"word": "In", "polygon": [[677, 975], [664, 953], [672, 948], [686, 970]]}
{"word": "The", "polygon": [[657, 942], [636, 896], [644, 891], [666, 937]]}
{"word": "running", "polygon": [[734, 1060], [690, 963], [712, 952], [751, 1054]]}
{"word": "running", "polygon": [[683, 953], [636, 860], [651, 851], [706, 941]]}
{"word": "The", "polygon": [[755, 1052], [738, 1000], [754, 992], [772, 1044]]}
{"word": "Mclaren", "polygon": [[733, 988], [676, 887], [694, 877], [751, 979]]}
{"word": "sumepet@fadanif.edu", "polygon": [[614, 843], [552, 707], [557, 703], [617, 840]]}
{"word": "32", "polygon": [[545, 698], [533, 684], [537, 681], [549, 695]]}
{"word": "new", "polygon": [[618, 839], [615, 811], [616, 810], [619, 838]]}
{"word": "bei", "polygon": [[613, 800], [606, 780], [607, 778], [614, 798]]}
{"word": "ist", "polygon": [[601, 770], [592, 755], [593, 753], [602, 768]]}
{"word": "GB", "polygon": [[586, 745], [575, 729], [577, 726], [587, 743]]}
{"word": "vielen", "polygon": [[569, 719], [543, 685], [547, 681], [571, 716]]}
{"word": "3", "polygon": [[535, 675], [529, 668], [533, 665], [539, 672]]}
{"word": "z", "polygon": [[523, 658], [518, 652], [521, 650], [525, 655]]}
{"word": "07/03/18", "polygon": [[619, 838], [605, 772], [605, 770], [620, 836]]}
{"word": "56", "polygon": [[600, 762], [591, 747], [591, 745], [600, 760]]}
{"word": "82", "polygon": [[585, 737], [576, 722], [576, 720], [585, 735]]}
{"word": "(388)", "polygon": [[569, 712], [548, 680], [552, 676], [571, 709]]}
{"word": "MERCADO.", "polygon": [[501, 636], [432, 473], [443, 461], [510, 627]]}
{"word": "95", "polygon": [[513, 623], [498, 582], [509, 572], [523, 614]]}
{"word": "SSID", "polygon": [[496, 575], [471, 501], [477, 490], [506, 564]]}
{"word": "pp", "polygon": [[470, 491], [447, 454], [459, 442], [476, 481]]}
{"word": "Kabelnetz", "polygon": [[525, 611], [465, 451], [474, 440], [533, 602]]}
{"word": "87", "polygon": [[538, 598], [523, 557], [535, 546], [554, 586]]}
{"word": "716,930", "polygon": [[520, 549], [475, 429], [485, 414], [533, 536]]}
{"word": "I", "polygon": [[472, 421], [469, 413], [477, 401], [480, 410]]}
{"word": "S\u00c9JOURS", "polygon": [[552, 587], [488, 434], [501, 417], [574, 571]]}
{"word": "REVIEWER", "polygon": [[871, 998], [771, 816], [782, 809], [886, 992]]}
{"word": "THE", "polygon": [[907, 985], [868, 915], [883, 908], [920, 980]]}
{"word": "VINYL", "polygon": [[852, 882], [795, 772], [813, 762], [870, 873]]}
{"word": "M\u00c9DI\u00c9VAUX", "polygon": [[945, 969], [837, 741], [866, 725], [976, 954]]}
{"word": "diese", "polygon": [[737, 763], [709, 703], [719, 697], [747, 757]]}
{"word": "ins", "polygon": [[706, 697], [690, 663], [698, 657], [715, 690]]}
{"word": "Ihr", "polygon": [[686, 657], [665, 622], [673, 615], [694, 650]]}
{"word": "wir", "polygon": [[661, 615], [639, 580], [649, 572], [670, 609]]}
{"word": "1,", "polygon": [[636, 573], [622, 552], [634, 543], [647, 564]]}
{"word": "Haz", "polygon": [[750, 755], [730, 712], [740, 706], [759, 749]]}
{"word": "TAILANDIA", "polygon": [[727, 706], [657, 579], [667, 572], [737, 699]]}
{"word": "the", "polygon": [[762, 747], [746, 710], [758, 703], [773, 741]]}
{"word": "Y", "polygon": [[744, 703], [736, 687], [746, 681], [754, 696]]}
{"word": "O", "polygon": [[732, 681], [723, 665], [733, 659], [742, 674]]}
{"word": "repeated", "polygon": [[719, 659], [666, 564], [681, 554], [732, 651]]}
{"word": "prominent", "polygon": [[609, 533], [549, 385], [563, 374], [625, 522]]}
{"word": "asian", "polygon": [[626, 522], [591, 438], [606, 427], [643, 511]]}
{"word": "and", "polygon": [[587, 424], [562, 370], [572, 359], [601, 414]]}
{"word": "Knowledge", "polygon": [[644, 510], [564, 346], [573, 334], [660, 500]]}
{"word": "noting", "polygon": [[661, 499], [614, 404], [625, 394], [675, 488]]}
{"word": "the", "polygon": [[607, 391], [578, 341], [589, 330], [617, 380]]}
{"word": "And", "polygon": [[676, 488], [647, 431], [662, 420], [692, 477]]}
{"word": "Resulted", "polygon": [[640, 417], [570, 283], [585, 271], [653, 406]]}
{"word": "Deinem", "polygon": [[1066, 913], [1021, 825], [1036, 817], [1081, 907]]}
{"word": "v", "polygon": [[1011, 794], [1004, 778], [1014, 773], [1022, 788]]}
{"word": "8.", "polygon": [[992, 749], [981, 720], [991, 714], [1002, 744]]}
{"word": "television", "polygon": [[1101, 898], [1028, 751], [1042, 743], [1117, 891]]}
{"word": "5,", "polygon": [[1016, 721], [1003, 692], [1017, 684], [1031, 712]]}
{"word": "1", "polygon": [[1142, 879], [1134, 864], [1149, 857], [1156, 872]]}
{"word": "c", "polygon": [[1122, 832], [1115, 817], [1127, 812], [1134, 827]]}
{"word": "d", "polygon": [[1097, 790], [1088, 774], [1104, 766], [1112, 782]]}
{"word": "O.", "polygon": [[1074, 745], [1059, 716], [1074, 708], [1089, 737]]}
{"word": "5", "polygon": [[1043, 688], [1035, 674], [1049, 666], [1058, 680]]}
{"word": "7", "polygon": [[1183, 860], [1174, 844], [1190, 836], [1199, 852]]}
{"word": "dd", "polygon": [[1155, 815], [1139, 783], [1155, 775], [1173, 807]]}
{"word": "barri\u00e8res", "polygon": [[1125, 753], [1055, 623], [1071, 614], [1140, 745]]}
{"word": "D'ENGAGER", "polygon": [[940, 644], [829, 462], [847, 450], [955, 635]]}
{"word": "boluwac.co.uk", "polygon": [[960, 632], [842, 423], [863, 411], [973, 622]]}
{"word": "1", "polygon": [[978, 619], [968, 602], [985, 592], [995, 609]]}
{"word": "5671", "polygon": [[963, 594], [928, 523], [945, 511], [980, 583]]}
{"word": "1,764", "polygon": [[925, 514], [885, 437], [905, 423], [944, 501]]}
{"word": "1", "polygon": [[1002, 605], [992, 588], [1011, 576], [1021, 593]]}
{"word": "891", "polygon": [[987, 579], [960, 528], [978, 516], [1007, 568]]}
{"word": "101", "polygon": [[956, 519], [931, 468], [945, 456], [973, 507]]}
{"word": "p", "polygon": [[930, 457], [921, 438], [936, 425], [945, 444]]}
{"word": "2", "polygon": [[913, 433], [905, 416], [920, 404], [928, 420]]}
{"word": "zowop.co.uk", "polygon": [[1029, 589], [927, 401], [950, 385], [1056, 574]]}
{"word": "since", "polygon": [[799, 395], [769, 335], [787, 325], [816, 384]]}
{"word": "the", "polygon": [[757, 326], [734, 284], [755, 271], [779, 313]]}
{"word": "early", "polygon": [[729, 272], [703, 207], [727, 188], [757, 254]]}
{"word": "rare", "polygon": [[839, 370], [815, 318], [827, 310], [852, 362]]}
{"word": "khurja", "polygon": [[802, 309], [760, 231], [788, 213], [830, 291]]}
{"word": "is", "polygon": [[760, 216], [750, 196], [766, 185], [776, 206]]}
{"word": "in", "polygon": [[874, 347], [863, 324], [876, 315], [887, 338]]}
{"word": "company", "polygon": [[859, 310], [805, 206], [823, 192], [880, 297]]}
{"word": "nd", "polygon": [[793, 199], [778, 169], [793, 156], [808, 187]]}
{"word": "Quilty", "polygon": [[907, 326], [863, 242], [891, 223], [937, 307]]}
{"word": "Leaves", "polygon": [[858, 229], [811, 148], [828, 133], [877, 215]]}
{"word": "On", "polygon": [[805, 136], [792, 110], [805, 97], [818, 123]]}
